vqe_portfolio/__init__.py
vqe_portfolio/__main__.py
vqe_portfolio/ansatz.py
vqe_portfolio/binary.py
vqe_portfolio/cli.py
vqe_portfolio/data.py
vqe_portfolio/fractional.py
vqe_portfolio/frontier.py
vqe_portfolio/metrics.py
vqe_portfolio/optimize.py
vqe_portfolio/plotting.py
vqe_portfolio/types.py
vqe_portfolio/utils.py
vqe_portfolio-0.1.2.dist-info/licenses/LICENSE
vqe_portfolio-0.1.2.dist-info/METADATA
vqe_portfolio-0.1.2.dist-info/WHEEL
vqe_portfolio-0.1.2.dist-info/entry_points.txt
vqe_portfolio-0.1.2.dist-info/top_level.txt
vqe_portfolio-0.1.2.dist-info/RECORD
