Metadata-Version: 2.4
Name: vqe-portfolio
Version: 0.1.2
Summary: VQE-based portfolio optimization with PennyLane
Author: Sid Richards
License-Expression: MIT
Project-URL: Repository, https://github.com/SidRichardsQuantum/VQE_Portfolio_Optimization
Project-URL: Issues, https://github.com/SidRichardsQuantum/VQE_Portfolio_Optimization/issues
Keywords: quantum,vqe,portfolio-optimization,pennylane,finance
Classifier: Programming Language :: Python :: 3
Classifier: Programming Language :: Python :: 3 :: Only
Classifier: Operating System :: OS Independent
Requires-Python: >=3.10
License-File: LICENSE
Requires-Dist: numpy<3.0,>=1.26
Requires-Dist: matplotlib<4.0,>=3.8
Requires-Dist: pennylane<1.0,>=0.35
Provides-Extra: dev
Requires-Dist: pytest<9,>=8; extra == "dev"
Requires-Dist: ruff<1.0,>=0.6; extra == "dev"
Requires-Dist: build<2.0,>=1.2; extra == "dev"
Requires-Dist: twine<7,>=6; extra == "dev"
Provides-Extra: markowitz
Requires-Dist: cvxpy<2.0,>=1.4; extra == "markowitz"
Requires-Dist: osqp<1.0,>=0.6; extra == "markowitz"
Provides-Extra: notebooks
Requires-Dist: jupyter>=1.0; extra == "notebooks"
Requires-Dist: jupytext<2.0,>=1.16; extra == "notebooks"
Provides-Extra: data
Requires-Dist: pandas<3.0,>=2.0; extra == "data"
Requires-Dist: yfinance<0.3.0,>=0.2.40; extra == "data"
Requires-Dist: scikit-learn<2.0,>=1.4; extra == "data"
Dynamic: license-file
